pubtools/_quay/__init__.py
pubtools/_quay/clear_repo.py
pubtools/_quay/command_executor.py
pubtools/_quay/container_image_pusher.py
pubtools/_quay/exceptions.py
pubtools/_quay/hooks.py
pubtools/_quay/iib_operations.py
pubtools/_quay/image_untagger.py
pubtools/_quay/item_processor.py
pubtools/_quay/manifest_list_merger.py
pubtools/_quay/merge_manifest_list.py
pubtools/_quay/models.py
pubtools/_quay/operator_pusher.py
pubtools/_quay/push_docker.py
pubtools/_quay/quay_api_client.py
pubtools/_quay/quay_client.py
pubtools/_quay/quay_session.py
pubtools/_quay/remove_repo.py
pubtools/_quay/security_manifest_pusher.py
pubtools/_quay/signer_wrapper.py
pubtools/_quay/tag_docker.py
pubtools/_quay/tag_images.py
pubtools/_quay/types.py
pubtools/_quay/untag_images.py
pubtools/_quay/utils/__init__.py
pubtools/_quay/utils/misc.py
pubtools_quay-0.36.0.dist-info/licenses/LICENSE
pubtools_quay-0.36.0.dist-info/METADATA
pubtools_quay-0.36.0.dist-info/WHEEL
pubtools_quay-0.36.0.dist-info/entry_points.txt
pubtools_quay-0.36.0.dist-info/top_level.txt
pubtools_quay-0.36.0.dist-info/RECORD
