Metadata-Version: 2.4
Name: pubtools-quay
Version: 0.36.0
Summary: Pubtools-quay
Home-page: https://github.com/release-engineering/pubtools-quay
Author: Lubomir Gallovic
Author-email: lgallovi@redhat.com
Classifier: Development Status :: 3 - Alpha
Classifier: Intended Audience :: Developers
Classifier: Programming Language :: Python
Classifier: Programming Language :: Python :: 3
Classifier: Programming Language :: Python :: 3.7
Classifier: Programming Language :: Python :: Implementation :: CPython
Classifier: Programming Language :: Python :: Implementation :: PyPy
Requires-Python: >=3.6
License-File: LICENSE
Requires-Dist: setuptools
Requires-Dist: pyrsistent
Requires-Dist: pushcollector
Requires-Dist: paramiko
Requires-Dist: requests
Requires-Dist: pubtools-pyxis>=1.3.6
Requires-Dist: python-qpid-proton
Requires-Dist: monotonic
Requires-Dist: docker
Requires-Dist: pubtools>=1.4.0
Requires-Dist: iiblib
Requires-Dist: pubtools-iib
Requires-Dist: kerberos
Requires-Dist: marshmallow
Requires-Dist: urllib3<2
Requires-Dist: pubtools-sign>=0.0.11
Requires-Dist: docker
Provides-Extra: rest
Requires-Dist: Sphinx; extra == "rest"
Dynamic: author
Dynamic: author-email
Dynamic: classifier
Dynamic: description
Dynamic: description-content-type
Dynamic: home-page
Dynamic: license-file
Dynamic: provides-extra
Dynamic: requires-dist
Dynamic: requires-python
Dynamic: summary
